zabbix_controller/__init__.py
zabbix_controller/call_command.py
zabbix_controller/cli.py
zabbix_controller/hosts/__init__.py
zabbix_controller/hosts/apis.py
zabbix_controller/hosts/command.py
zabbix_controller/hosts/graphs.py
zabbix_controller/hosts/interfaces.py
zabbix_controller/utils.py
zabbix_controller/zabbix_ctl.py
zabbix_controller-0.1.19.dist-info/entry_points.txt
zabbix_controller-0.1.19.dist-info/LICENSE
zabbix_controller-0.1.19.dist-info/WHEEL
zabbix_controller-0.1.19.dist-info/METADATA
zabbix_controller-0.1.19.dist-info/RECORD
