Metadata-Version: 2.1
Name: zabbix-controller
Version: 0.1.19
Summary: 
Home-page: https://github.com/hamadakafu/zabbix-controller
Author: hamadakafu
Author-email: kafu.h1998@gmail.com
Requires-Python: >=3.7,<4.0
Classifier: Programming Language :: Python :: 3
Classifier: Programming Language :: Python :: 3.7
Requires-Dist: bullet (>=2.1,<3.0)
Requires-Dist: click (>=7.0,<8.0)
Requires-Dist: pyzabbix (>=0.7.5,<0.8.0)
Project-URL: Repository, https://github.com/hamadakafu/zabbix-controller
